IP_GPS/IP_GPS.py
IP_GPS/__init__.py
IP_GPS-0.0.1.dist-info/LICENSE
IP_GPS-0.0.1.dist-info/METADATA
IP_GPS-0.0.1.dist-info/WHEEL
IP_GPS-0.0.1.dist-info/top_level.txt
IP_GPS-0.0.1.dist-info/RECORD
