Metadata-Version: 2.1
Name: IP-GPS
Version: 0.0.1
Summary: IP_GPS
Home-page: UNKNOWN
Author: FreetBash
Author-email: 3141495167@qq.com
License: MIT
Platform: UNKNOWN
